{
    "FINAL PLANETARY PARAMETERS": {
        "Mid-Transit Time (Tmid)": "2457862.82713 +/- 0.00061 BJD_TDB",
        "Ratio of Planet to Stellar Radius (Rp/R*)": "0.196 +/- 0.016",
        "Transit depth (Rp/Rs)^2": "3.84 +/- 0.63 [%]",
        "Semi Major Axis/Star Radius (a/Rs)": "5.88 +/- 0.39 ",
        "Airmass coefficient 1 (a1)": "1.166 +/- 0.019",
        "Airmass coefficient 2 (a2)": "-0.1264 +/- 0.0045",
        "Scatter in the residuals of the lightcurve fit is": "1.65 %",
        "Best Comparison Star": "None",
        "Optimal Aperture": "4.39",
        "Optimal Annulus": "13.43",
        "Transit Duration (day)": "0.063 +/- 0.0089"
    }
}